michaelPanPrintLib/__init__.py
michaelPanPrintLib/change_print.py
michaelPanPrintLib/install_lib.py
michaelPanPrintLib-0.0.6.dist-info/LICENSE
michaelPanPrintLib-0.0.6.dist-info/METADATA
michaelPanPrintLib-0.0.6.dist-info/WHEEL
michaelPanPrintLib-0.0.6.dist-info/top_level.txt
michaelPanPrintLib-0.0.6.dist-info/RECORD
